{
	"app-id": "org.gottcode.NovProg",
	"runtime": "org.kde.Platform",
	"runtime-version": "5.11",
	"sdk": "org.kde.Sdk",
	"command": "novprog",
	"rename-icon": "novprog",
	"rename-desktop-file": "novprog.desktop",
	"rename-appdata-file": "novprog.appdata.xml",
	"finish-args": [
		"--socket=wayland",
		"--socket=x11",
		"--share=ipc",
		"--filesystem=xdg-config/kdeglobals:ro",
		"--talk-name=com.canonical.AppMenu.Registrar"
	],
	"modules": [
		{
			"name": "novprog",
			"buildsystem": "qmake",
			"sources": [
				{
					"type": "archive",
					"url": "https://gottcode.org/novprog/novprog-3.1.5-src.tar.bz2",
					"sha256": "0a777d1c933f1994d02c3118f6a1d027da07d0028184dcb29c543cc7d7b46a8a"
				}
			]
		}
	]
}
